pycerpt/__init__.py
pycerpt/cli.py
pycerpt/excerpt.py
pycerpt/extractor.py
pycerpt/pdfgen.py
pycerpt/pycerpt.py
pycerpt-0.2.1.dist-info/LICENSE
pycerpt-0.2.1.dist-info/METADATA
pycerpt-0.2.1.dist-info/WHEEL
pycerpt-0.2.1.dist-info/entry_points.txt
pycerpt-0.2.1.dist-info/top_level.txt
pycerpt-0.2.1.dist-info/RECORD
