Metadata-Version: 2.1
Name: pycerpt
Version: 0.2.1
Summary: A cli utility for generating excerpts from highlighted PDFs
Home-page: https://github.com/MerlinB/pycerpt
Author: Merlin Buczek
Author-email: merlin.buczek@gmail.com
License: UNKNOWN
Platform: UNKNOWN
Classifier: Programming Language :: Python :: 3.6
Classifier: Programming Language :: Python :: 3.7
Classifier: License :: CC0 1.0 Universal (CC0 1.0) Public Domain Dedication
Classifier: Operating System :: OS Independent
Requires-Dist: Click
Requires-Dist: pdfminer.six
Requires-Dist: chardet
Provides-Extra: pdf
Requires-Dist: reportlab ; extra == 'pdf'
Provides-Extra: testing
Requires-Dist: tox ; extra == 'testing'
